python_uv/__init__.py
python_uv/advanced.py
python_uv/data.py
python_uv/main.py
python_uv/py.typed
python_uv-0.0.37.dist-info/METADATA
python_uv-0.0.37.dist-info/WHEEL
python_uv-0.0.37.dist-info/entry_points.txt
python_uv-0.0.37.dist-info/licenses/LICENSE
python_uv-0.0.37.dist-info/RECORD
