Metadata-Version: 2.3
Name: python-uv
Version: 0.0.37
Summary: python template package
Project-URL: Homepage, https://github.com/aittcuszz/python-uv
Project-URL: Issues, https://github.com/atticuszz/python-uv/issues
Project-URL: documentation, https://atticuszz.github.io/python-uv/
Project-URL: Changelog, https://github.com/atticuszz/python-uv/blob/main/CHANGELOG.md
Author-email: "A.J.Zeller" <zhouge1831@gmail.com>
Maintainer-email: "A.J.Zeller" <zhouge1831@gmail.com>
License: MIT License
License-File: LICENSE
Classifier: License :: OSI Approved :: MIT License
Classifier: Programming Language :: Python
Classifier: Programming Language :: Python :: 3 :: Only
Classifier: Programming Language :: Python :: 3.10
Classifier: Programming Language :: Python :: 3.11
Classifier: Programming Language :: Python :: 3.12
Classifier: Programming Language :: Python :: 3.13
Requires-Python: >=3.10
